Workbook

Sheet Pipeline Data
A1: Opp ID | B1: Opportunity Name | C1: Account Name | D1: Region | E1: Sales Rep | F1: Stage | G1: Amount ($) | H1: Probability (%) | I1: Weighted Amount ($) | J1: Close Date | K1: Lead Source | L1: Industry | M1: Notes
A2: OPP-001 | B2: CloudSync Enterprise License | C2: Meridian Health | D2: AMER | E2: James Okafor | F2: Proposal/Price Quote | G2: 120000 | H2: 0.75 | I2: =G2*H2 -> 90000 | J2: 45838 | K2: Outbound | L2: Healthcare | M2: Renewal upgrade
A3: OPP-002 | B3: Analytics Pro Suite | C3: Apex Retail Group | D3: AMER | E3: James Okafor | F3: Closed Won | G3: 85000 | H3: 1 | I3: =G3*H3 -> 85000 | J3: 45792 | K3: Inbound | L3: Retail
A4: OPP-003 | B4: DataBridge Platform | C4: Franklin Capital | D4: AMER | E4: Sarah Nwachukwu | F4: Needs Analysis | G4: 200000 | H4: 0.2 | I4: =G4*H4 -> 40000 | J4: 45869 | K4: Partner Referral | L4: Finance | M4: Early stage
A5: OPP-004 | B5: NovaTech Core Bundle | C5: TechVentures Inc. | D5: AMER | E5: Sarah Nwachukwu | F5: Value Proposition | G5: 55000 | H5: 0.5 | I5: =G5*H5 -> 27500 | J5: 45823 | K5: Web | L5: Technology | M5: Demo completed
A6: OPP-005 | B6: Premium Support Pack | C6: GlobalEdge LLC | D6: AMER | E6: James Okafor | F6: Closed Lost | G6: 30000 | H6: 0 | I6: =G6*H6 -> 0 | J6: 45777 | K6: Outbound | L6: Consulting | M6: Lost to competitor
A7: OPP-006 | B7: AI Insights Module | C7: StreamlineOps | D7: AMER | E7: Carlos Diaz | F7: Perception Analysis | G7: 95000 | H7: 0.65 | I7: =G7*H7 -> 61750 | J7: 45853 | K7: Event | L7: Manufacturing | M7: Pilot approved
A8: OPP-007 | B8: SMB Starter Plan | C8: Bright Ideas Co. | D8: AMER | E8: Carlos Diaz | F8: Needs Analysis | G8: 22000 | H8: 0.2 | I8: =G8*H8 -> 4400 | J8: 45900 | K8: Inbound | L8: Education
A9: OPP-008 | B9: Enterprise Suite Renewal | C9: Hartwell Corp | D9: AMER | E9: Sarah Nwachukwu | F9: Proposal/Price Quote | G9: 175000 | H9: 0.75 | I9: =G9*H9 -> 131250 | J9: 45838 | K9: Outbound | L9: Financial Services | M9: Legal reviewing
A10: OPP-009 | B10: CloudSync EMEA Bundle | C10: Nordic Systems AB | D10: EMEA | E10: Priya Sharma | F10: Closed Won | G10: 110000 | H10: 1 | I10: =G10*H10 -> 110000 | J10: 45797 | K10: Partner Referral | L10: Technology
A11: OPP-010 | B11: DataBridge EU | C11: Vega Pharmaceuticals | D11: EMEA | E11: Priya Sharma | F11: Value Proposition | G11: 145000 | H11: 0.5 | I11: =G11*H11 -> 72500 | J11: 45869 | K11: Inbound | L11: Pharma | M11: GDPR review pending
A12: OPP-011 | B12: Analytics Platform | C12: Atlas Logistics | D12: EMEA | E12: Tobias Müller | F12: Proposal/Price Quote | G12: 88000 | H12: 0.75 | I12: =G12*H12 -> 66000 | J12: 45823 | K12: Outbound | L12: Logistics
A13: OPP-012 | B13: Core License Expansion | C13: Luminos Bank | D13: EMEA | E13: Tobias Müller | F13: Needs Analysis | G13: 250000 | H13: 0.2 | I13: =G13*H13 -> 50000 | J13: 45930 | K13: Inbound | L13: Banking | M13: Large deal, long cycle
A14: OPP-013 | B14: NovaTech Starter | C14: Greenwave Energy | D14: EMEA | E14: Priya Sharma | F14: Perception Analysis | G14: 40000 | H14: 0.65 | I14: =G14*H14 -> 26000 | J14: 45869 | K14: Web | L14: Energy
A15: OPP-014 | B15: Premium Support EMEA | C15: Fischer & Partners | D15: EMEA | E15: Tobias Müller | F15: Closed Won | G15: 62000 | H15: 1 | I15: =G15*H15 -> 62000 | J15: 45808 | K15: Partner Referral | L15: Legal
A16: OPP-015 | B16: AI Insights EMEA | C16: Solaris Tech GmbH | D16: EMEA | E16: Priya Sharma | F16: Value Proposition | G16: 98000 | H16: 0.5 | I16: =G16*H16 -> 49000 | J16: 45884 | K16: Event | L16: Technology | M16: Evaluation underway
A17: OPP-016 | B17: CloudSync APAC | C17: Tanaka Industries | D17: APAC | E17: Lin Wei | F17: Closed Won | G17: 130000 | H17: 1 | I17: =G17*H17 -> 130000 | J17: 45777 | K17: Inbound | L17: Manufacturing
A18: OPP-017 | B18: Analytics Suite APAC | C18: Oceanic Finance | D18: APAC | E18: Lin Wei | F18: Proposal/Price Quote | G18: 77000 | H18: 0.75 | I18: =G18*H18 -> 57750 | J18: 45838 | K18: Outbound | L18: Finance
A19: OPP-018 | B19: DataBridge ANZ | C19: Skyline Properties | D19: APAC | E19: Raj Patel | F19: Needs Analysis | G19: 165000 | H19: 0.2 | I19: =G19*H19 -> 33000 | J19: 45930 | K19: Partner Referral | L19: Real Estate | M19: New logo
A20: OPP-019 | B20: Core Bundle SEA | C20: PacificNet Pte Ltd | D20: APAC | E20: Raj Patel | F20: Value Proposition | G20: 92000 | H20: 0.5 | I20: =G20*H20 -> 46000 | J20: 45869 | K20: Inbound | L20: Telecom
A21: OPP-020 | B21: Enterprise Expansion | C21: HorizonTech KR | D21: APAC | E21: Lin Wei | F21: Perception Analysis | G21: 210000 | H21: 0.65 | I21: =G21*H21 -> 136500 | J21: 45900 | K21: Outbound | L21: Technology
A22: OPP-021 | B22: AI Module APAC | C22: AustraliaCare | D22: APAC | E22: Raj Patel | F22: Proposal/Price Quote | G22: 58000 | H22: 0.75 | I22: =G22*H22 -> 43500 | J22: 45853 | K22: Event | L22: Healthcare
A23: OPP-022 | B23: SMB Package SEA | C23: ByteLogic MY | D23: APAC | E23: Lin Wei | F23: Closed Lost | G23: 18000 | H23: 0 | I23: =G23*H23 -> 0 | J23: 45778 | K23: Web | L23: Technology | M23: Budget freeze
A24: TOTALS | G24: =SUM(G2:G23) -> 2325000 | I24: =SUM(I2:I23) -> 1322150

Sheet Best Case
A1: NovaTech Solutions - Q2/Q3 2025 Revenue Forecast | Best Case
A3: KEY ASSUMPTIONS
A4: Scenario Multiplier: | B4: 1.15 | C4: 1.15
A5: Probability Adjustment: | B5: 0.15 | C5: +15% uplift
A6: Quota per Rep ($): | B6: 500000 | C6: Annual quota per sales rep
A7: Number of Reps: | B7: 5 | C7: Active quota-carrying reps
A9: PIPELINE BY REGION - WEIGHTED FORECAST
A10: Region | B10: Total Pipeline ($) | C10: Open Opps | D10: Weighted Pipeline ($) | E10: Scenario Forecast (1.15) | F10: Quota ($) | G10: Attainment (%) | H10: Gap to Quota ($)
A11: AMER | B11: =SUMPRODUCT(('Pipeline Data'!D$2:D$23="AMER")*('Pipeline Data'!F$2:F$23<>"Closed Lost")*('Pipeline Data'!G$2:G$23)) -> 752000 | C11: =COUNTIFS('Pipeline Data'!D$2:D$23,"AMER",'Pipeline Data'!F$2:F$23,"<>Closed Lost",'Pipeline Data'!F$2:F$23,"<>Closed Won") -> 6 | D11: =SUMPRODUCT(('Pipeline Data'!D$2:D$23="AMER")*('Pipeline Data'!F$2:F$23<>"Closed Lost")*('Pipeline Data'!I$2:I$23)) -> 439900 | E11: =D11*$B$4 -> 505885 | F11: =$B$6*$B$7/3 -> 833333.33 | G11: =IF(F11=0,0,E11/F11) -> 0.607062 | H11: =E11-F11 -> -327448.33
A12: EMEA | B12: =SUMPRODUCT(('Pipeline Data'!D$2:D$23="EMEA")*('Pipeline Data'!F$2:F$23<>"Closed Lost")*('Pipeline Data'!G$2:G$23)) -> 793000 | C12: =COUNTIFS('Pipeline Data'!D$2:D$23,"EMEA",'Pipeline Data'!F$2:F$23,"<>Closed Lost",'Pipeline Data'!F$2:F$23,"<>Closed Won") -> 5 | D12: =SUMPRODUCT(('Pipeline Data'!D$2:D$23="EMEA")*('Pipeline Data'!F$2:F$23<>"Closed Lost")*('Pipeline Data'!I$2:I$23)) -> 435500 | E12: =D12*$B$4 -> 500825 | F12: =$B$6*$B$7/3 -> 833333.33 | G12: =IF(F12=0,0,E12/F12) -> 0.60099 | H12: =E12-F12 -> -332508.33
A13: APAC | B13: =SUMPRODUCT(('Pipeline Data'!D$2:D$23="APAC")*('Pipeline Data'!F$2:F$23<>"Closed Lost")*('Pipeline Data'!G$2:G$23)) -> 732000 | C13: =COUNTIFS('Pipeline Data'!D$2:D$23,"APAC",'Pipeline Data'!F$2:F$23,"<>Closed Lost",'Pipeline Data'!F$2:F$23,"<>Closed Won") -> 5 | D13: =SUMPRODUCT(('Pipeline Data'!D$2:D$23="APAC")*('Pipeline Data'!F$2:F$23<>"Closed Lost")*('Pipeline Data'!I$2:I$23)) -> 446750 | E13: =D13*$B$4 -> 513762.5 | F13: =$B$6*$B$7/3 -> 833333.33 | G13: =IF(F13=0,0,E13/F13) -> 0.616515 | H13: =E13-F13 -> -319570.83
A14: TOTAL | B14: =SUM(B11:B13) -> 2277000 | C14: =SUM(C11:C13) -> 16 | D14: =SUM(D11:D13) -> 1322150 | E14: =SUM(E11:E13) -> 1520472.5 | F14: =SUM(F11:F13) -> 2500000 | G14: =SUM(G11:G13) -> 1.824567 | H14: =SUM(H11:H13) -> -979527.5
A16: QUOTA ATTAINMENT BY REP
A17: Sales Rep | B17: Region | C17: Closed Won ($) | D17: Pipeline (Weighted) ($) | E17: Scenario Total (1.15) | F17: Annual Quota ($) | G17: Attainment (%)
A18: James Okafor | B18: AMER | C18: =SUMPRODUCT(('Pipeline Data'!E$2:E$23="James Okafor")*('Pipeline Data'!F$2:F$23="Closed Won")*('Pipeline Data'!G$2:G$23)) -> 85000 | D18: =SUMPRODUCT(('Pipeline Data'!E$2:E$23="James Okafor")*('Pipeline Data'!F$2:F$23<>"Closed Won")*('Pipeline Data'!F$2:F$23<>"Closed Lost")*('Pipeline Data'!I$2:I$23)) -> 90000 | E18: =C18+D18*$B$4 -> 188500 | F18: =$B$6 -> 500000 | G18: =IF(F18=0,0,E18/F18) -> 0.377
A19: Sarah Nwachukwu | B19: AMER | C19: =SUMPRODUCT(('Pipeline Data'!E$2:E$23="Sarah Nwachukwu")*('Pipeline Data'!F$2:F$23="Closed Won")*('Pipeline Data'!G$2:G$23)) -> 0 | D19: =SUMPRODUCT(('Pipeline Data'!E$2:E$23="Sarah Nwachukwu")*('Pipeline Data'!F$2:F$23<>"Closed Won")*('Pipeline Data'!F$2:F$23<>"Closed Lost")*('Pipeline Data'!I$2:I$23)) -> 198750 | E19: =C19+D19*$B$4 -> 228562.5 | F19: =$B$6 -> 500000 | G19: =IF(F19=0,0,E19/F19) -> 0.457125
A20: Carlos Diaz | B20: AMER | C20: =SUMPRODUCT(('Pipeline Data'!E$2:E$23="Carlos Diaz")*('Pipeline Data'!F$2:F$23="Closed Won")*('Pipeline Data'!G$2:G$23)) -> 0 | D20: =SUMPRODUCT(('Pipeline Data'!E$2:E$23="Carlos Diaz")*('Pipeline Data'!F$2:F$23<>"Closed Won")*('Pipeline Data'!F$2:F$23<>"Closed Lost")*('Pipeline Data'!I$2:I$23)) -> 66150 | E20: =C20+D20*$B$4 -> 76072.5 | F20: =$B$6 -> 500000 | G20: =IF(F20=0,0,E20/F20) -> 0.152145
A21: Priya Sharma | B21: EMEA | C21: =SUMPRODUCT(('Pipeline Data'!E$2:E$23="Priya Sharma")*('Pipeline Data'!F$2:F$23="Closed Won")*('Pipeline Data'!G$2:G$23)) -> 110000 | D21: =SUMPRODUCT(('Pipeline Data'!E$2:E$23="Priya Sharma")*('Pipeline Data'!F$2:F$23<>"Closed Won")*('Pipeline Data'!F$2:F$23<>"Closed Lost")*('Pipeline Data'!I$2:I$23)) -> 147500 | E21: =C21+D21*$B$4 -> 279625 | F21: =$B$6 -> 500000 | G21: =IF(F21=0,0,E21/F21) -> 0.55925
A22: Tobias Müller | B22: EMEA | C22: =SUMPRODUCT(('Pipeline Data'!E$2:E$23="Tobias Müller")*('Pipeline Data'!F$2:F$23="Closed Won")*('Pipeline Data'!G$2:G$23)) -> 62000 | D22: =SUMPRODUCT(('Pipeline Data'!E$2:E$23="Tobias Müller")*('Pipeline Data'!F$2:F$23<>"Closed Won")*('Pipeline Data'!F$2:F$23<>"Closed Lost")*('Pipeline Data'!I$2:I$23)) -> 116000 | E22: =C22+D22*$B$4 -> 195400 | F22: =$B$6 -> 500000 | G22: =IF(F22=0,0,E22/F22) -> 0.3908
A23: Lin Wei | B23: APAC | C23: =SUMPRODUCT(('Pipeline Data'!E$2:E$23="Lin Wei")*('Pipeline Data'!F$2:F$23="Closed Won")*('Pipeline Data'!G$2:G$23)) -> 130000 | D23: =SUMPRODUCT(('Pipeline Data'!E$2:E$23="Lin Wei")*('Pipeline Data'!F$2:F$23<>"Closed Won")*('Pipeline Data'!F$2:F$23<>"Closed Lost")*('Pipeline Data'!I$2:I$23)) -> 194250 | E23: =C23+D23*$B$4 -> 353387.5 | F23: =$B$6 -> 500000 | G23: =IF(F23=0,0,E23/F23) -> 0.706775
A24: Raj Patel | B24: APAC | C24: =SUMPRODUCT(('Pipeline Data'!E$2:E$23="Raj Patel")*('Pipeline Data'!F$2:F$23="Closed Won")*('Pipeline Data'!G$2:G$23)) -> 0 | D24: =SUMPRODUCT(('Pipeline Data'!E$2:E$23="Raj Patel")*('Pipeline Data'!F$2:F$23<>"Closed Won")*('Pipeline Data'!F$2:F$23<>"Closed Lost")*('Pipeline Data'!I$2:I$23)) -> 122500 | E24: =C24+D24*$B$4 -> 140875 | F24: =$B$6 -> 500000 | G24: =IF(F24=0,0,E24/F24) -> 0.28175
A25: TOTAL | C25: =SUM(C18:C24) -> 387000 | D25: =SUM(D18:D24) -> 935150 | E25: =SUM(E18:E24) -> 1462422.5 | F25: =SUM(F18:F24) -> 3500000 | G25: =IF(F25=0,0,E25/F25) -> 0.417835

Sheet Worst Case
A1: NovaTech Solutions - Q2/Q3 2025 Revenue Forecast | Worst Case
A3: KEY ASSUMPTIONS
A4: Scenario Multiplier: | B4: 0.8 | C4: 0.80
A5: Probability Adjustment: | B5: -0.2 | C5: -20% haircut
A6: Quota per Rep ($): | B6: 500000 | C6: Annual quota per sales rep
A7: Number of Reps: | B7: 5 | C7: Active quota-carrying reps
A9: PIPELINE BY REGION - WEIGHTED FORECAST
A10: Region | B10: Total Pipeline ($) | C10: Open Opps | D10: Weighted Pipeline ($) | E10: Scenario Forecast (0.80) | F10: Quota ($) | G10: Attainment (%) | H10: Gap to Quota ($)
A11: AMER | B11: =SUMPRODUCT(('Pipeline Data'!D$2:D$23="AMER")*('Pipeline Data'!F$2:F$23<>"Closed Lost")*('Pipeline Data'!G$2:G$23)) -> 752000 | C11: =COUNTIFS('Pipeline Data'!D$2:D$23,"AMER",'Pipeline Data'!F$2:F$23,"<>Closed Lost",'Pipeline Data'!F$2:F$23,"<>Closed Won") -> 6 | D11: =SUMPRODUCT(('Pipeline Data'!D$2:D$23="AMER")*('Pipeline Data'!F$2:F$23<>"Closed Lost")*('Pipeline Data'!I$2:I$23)) -> 439900 | E11: =D11*$B$4 -> 351920 | F11: =$B$6*$B$7/3 -> 833333.33 | G11: =IF(F11=0,0,E11/F11) -> 0.422304 | H11: =E11-F11 -> -481413.33
A12: EMEA | B12: =SUMPRODUCT(('Pipeline Data'!D$2:D$23="EMEA")*('Pipeline Data'!F$2:F$23<>"Closed Lost")*('Pipeline Data'!G$2:G$23)) -> 793000 | C12: =COUNTIFS('Pipeline Data'!D$2:D$23,"EMEA",'Pipeline Data'!F$2:F$23,"<>Closed Lost",'Pipeline Data'!F$2:F$23,"<>Closed Won") -> 5 | D12: =SUMPRODUCT(('Pipeline Data'!D$2:D$23="EMEA")*('Pipeline Data'!F$2:F$23<>"Closed Lost")*('Pipeline Data'!I$2:I$23)) -> 435500 | E12: =D12*$B$4 -> 348400 | F12: =$B$6*$B$7/3 -> 833333.33 | G12: =IF(F12=0,0,E12/F12) -> 0.41808 | H12: =E12-F12 -> -484933.33
A13: APAC | B13: =SUMPRODUCT(('Pipeline Data'!D$2:D$23="APAC")*('Pipeline Data'!F$2:F$23<>"Closed Lost")*('Pipeline Data'!G$2:G$23)) -> 732000 | C13: =COUNTIFS('Pipeline Data'!D$2:D$23,"APAC",'Pipeline Data'!F$2:F$23,"<>Closed Lost",'Pipeline Data'!F$2:F$23,"<>Closed Won") -> 5 | D13: =SUMPRODUCT(('Pipeline Data'!D$2:D$23="APAC")*('Pipeline Data'!F$2:F$23<>"Closed Lost")*('Pipeline Data'!I$2:I$23)) -> 446750 | E13: =D13*$B$4 -> 357400 | F13: =$B$6*$B$7/3 -> 833333.33 | G13: =IF(F13=0,0,E13/F13) -> 0.42888 | H13: =E13-F13 -> -475933.33
A14: TOTAL | B14: =SUM(B11:B13) -> 2277000 | C14: =SUM(C11:C13) -> 16 | D14: =SUM(D11:D13) -> 1322150 | E14: =SUM(E11:E13) -> 1057720 | F14: =SUM(F11:F13) -> 2500000 | G14: =SUM(G11:G13) -> 1.269264 | H14: =SUM(H11:H13) -> -1442280
A16: QUOTA ATTAINMENT BY REP
A17: Sales Rep | B17: Region | C17: Closed Won ($) | D17: Pipeline (Weighted) ($) | E17: Scenario Total (0.80) | F17: Annual Quota ($) | G17: Attainment (%)
A18: James Okafor | B18: AMER | C18: =SUMPRODUCT(('Pipeline Data'!E$2:E$23="James Okafor")*('Pipeline Data'!F$2:F$23="Closed Won")*('Pipeline Data'!G$2:G$23)) -> 85000 | D18: =SUMPRODUCT(('Pipeline Data'!E$2:E$23="James Okafor")*('Pipeline Data'!F$2:F$23<>"Closed Won")*('Pipeline Data'!F$2:F$23<>"Closed Lost")*('Pipeline Data'!I$2:I$23)) -> 90000 | E18: =C18+D18*$B$4 -> 157000 | F18: =$B$6 -> 500000 | G18: =IF(F18=0,0,E18/F18) -> 0.314
A19: Sarah Nwachukwu | B19: AMER | C19: =SUMPRODUCT(('Pipeline Data'!E$2:E$23="Sarah Nwachukwu")*('Pipeline Data'!F$2:F$23="Closed Won")*('Pipeline Data'!G$2:G$23)) -> 0 | D19: =SUMPRODUCT(('Pipeline Data'!E$2:E$23="Sarah Nwachukwu")*('Pipeline Data'!F$2:F$23<>"Closed Won")*('Pipeline Data'!F$2:F$23<>"Closed Lost")*('Pipeline Data'!I$2:I$23)) -> 198750 | E19: =C19+D19*$B$4 -> 159000 | F19: =$B$6 -> 500000 | G19: =IF(F19=0,0,E19/F19) -> 0.318
A20: Carlos Diaz | B20: AMER | C20: =SUMPRODUCT(('Pipeline Data'!E$2:E$23="Carlos Diaz")*('Pipeline Data'!F$2:F$23="Closed Won")*('Pipeline Data'!G$2:G$23)) -> 0 | D20: =SUMPRODUCT(('Pipeline Data'!E$2:E$23="Carlos Diaz")*('Pipeline Data'!F$2:F$23<>"Closed Won")*('Pipeline Data'!F$2:F$23<>"Closed Lost")*('Pipeline Data'!I$2:I$23)) -> 66150 | E20: =C20+D20*$B$4 -> 52920 | F20: =$B$6 -> 500000 | G20: =IF(F20=0,0,E20/F20) -> 0.10584
A21: Priya Sharma | B21: EMEA | C21: =SUMPRODUCT(('Pipeline Data'!E$2:E$23="Priya Sharma")*('Pipeline Data'!F$2:F$23="Closed Won")*('Pipeline Data'!G$2:G$23)) -> 110000 | D21: =SUMPRODUCT(('Pipeline Data'!E$2:E$23="Priya Sharma")*('Pipeline Data'!F$2:F$23<>"Closed Won")*('Pipeline Data'!F$2:F$23<>"Closed Lost")*('Pipeline Data'!I$2:I$23)) -> 147500 | E21: =C21+D21*$B$4 -> 228000 | F21: =$B$6 -> 500000 | G21: =IF(F21=0,0,E21/F21) -> 0.456
A22: Tobias Müller | B22: EMEA | C22: =SUMPRODUCT(('Pipeline Data'!E$2:E$23="Tobias Müller")*('Pipeline Data'!F$2:F$23="Closed Won")*('Pipeline Data'!G$2:G$23)) -> 62000 | D22: =SUMPRODUCT(('Pipeline Data'!E$2:E$23="Tobias Müller")*('Pipeline Data'!F$2:F$23<>"Closed Won")*('Pipeline Data'!F$2:F$23<>"Closed Lost")*('Pipeline Data'!I$2:I$23)) -> 116000 | E22: =C22+D22*$B$4 -> 154800 | F22: =$B$6 -> 500000 | G22: =IF(F22=0,0,E22/F22) -> 0.3096
A23: Lin Wei | B23: APAC | C23: =SUMPRODUCT(('Pipeline Data'!E$2:E$23="Lin Wei")*('Pipeline Data'!F$2:F$23="Closed Won")*('Pipeline Data'!G$2:G$23)) -> 130000 | D23: =SUMPRODUCT(('Pipeline Data'!E$2:E$23="Lin Wei")*('Pipeline Data'!F$2:F$23<>"Closed Won")*('Pipeline Data'!F$2:F$23<>"Closed Lost")*('Pipeline Data'!I$2:I$23)) -> 194250 | E23: =C23+D23*$B$4 -> 285400 | F23: =$B$6 -> 500000 | G23: =IF(F23=0,0,E23/F23) -> 0.5708
A24: Raj Patel | B24: APAC | C24: =SUMPRODUCT(('Pipeline Data'!E$2:E$23="Raj Patel")*('Pipeline Data'!F$2:F$23="Closed Won")*('Pipeline Data'!G$2:G$23)) -> 0 | D24: =SUMPRODUCT(('Pipeline Data'!E$2:E$23="Raj Patel")*('Pipeline Data'!F$2:F$23<>"Closed Won")*('Pipeline Data'!F$2:F$23<>"Closed Lost")*('Pipeline Data'!I$2:I$23)) -> 122500 | E24: =C24+D24*$B$4 -> 98000 | F24: =$B$6 -> 500000 | G24: =IF(F24=0,0,E24/F24) -> 0.196
A25: TOTAL | C25: =SUM(C18:C24) -> 387000 | D25: =SUM(D18:D24) -> 935150 | E25: =SUM(E18:E24) -> 1135120 | F25: =SUM(F18:F24) -> 3500000 | G25: =IF(F25=0,0,E25/F25) -> 0.32432

Sheet Commit
A1: NovaTech Solutions - Q2/Q3 2025 Revenue Forecast | Commit
A3: KEY ASSUMPTIONS
A4: Scenario Multiplier: | B4: 1 | C4: 1.00
A5: Probability Adjustment: | B5: 0 | C5: Base (no adj)
A6: Quota per Rep ($): | B6: 500000 | C6: Annual quota per sales rep
A7: Number of Reps: | B7: 5 | C7: Active quota-carrying reps
A9: PIPELINE BY REGION - WEIGHTED FORECAST
A10: Region | B10: Total Pipeline ($) | C10: Open Opps | D10: Weighted Pipeline ($) | E10: Scenario Forecast (1.00) | F10: Quota ($) | G10: Attainment (%) | H10: Gap to Quota ($)
A11: AMER | B11: =SUMPRODUCT(('Pipeline Data'!D$2:D$23="AMER")*('Pipeline Data'!F$2:F$23<>"Closed Lost")*('Pipeline Data'!G$2:G$23)) -> 752000 | C11: =COUNTIFS('Pipeline Data'!D$2:D$23,"AMER",'Pipeline Data'!F$2:F$23,"<>Closed Lost",'Pipeline Data'!F$2:F$23,"<>Closed Won") -> 6 | D11: =SUMPRODUCT(('Pipeline Data'!D$2:D$23="AMER")*('Pipeline Data'!F$2:F$23<>"Closed Lost")*('Pipeline Data'!I$2:I$23)) -> 439900 | E11: =D11*$B$4 -> 439900 | F11: =$B$6*$B$7/3 -> 833333.33 | G11: =IF(F11=0,0,E11/F11) -> 0.52788 | H11: =E11-F11 -> -393433.33
A12: EMEA | B12: =SUMPRODUCT(('Pipeline Data'!D$2:D$23="EMEA")*('Pipeline Data'!F$2:F$23<>"Closed Lost")*('Pipeline Data'!G$2:G$23)) -> 793000 | C12: =COUNTIFS('Pipeline Data'!D$2:D$23,"EMEA",'Pipeline Data'!F$2:F$23,"<>Closed Lost",'Pipeline Data'!F$2:F$23,"<>Closed Won") -> 5 | D12: =SUMPRODUCT(('Pipeline Data'!D$2:D$23="EMEA")*('Pipeline Data'!F$2:F$23<>"Closed Lost")*('Pipeline Data'!I$2:I$23)) -> 435500 | E12: =D12*$B$4 -> 435500 | F12: =$B$6*$B$7/3 -> 833333.33 | G12: =IF(F12=0,0,E12/F12) -> 0.5226 | H12: =E12-F12 -> -397833.33
A13: APAC | B13: =SUMPRODUCT(('Pipeline Data'!D$2:D$23="APAC")*('Pipeline Data'!F$2:F$23<>"Closed Lost")*('Pipeline Data'!G$2:G$23)) -> 732000 | C13: =COUNTIFS('Pipeline Data'!D$2:D$23,"APAC",'Pipeline Data'!F$2:F$23,"<>Closed Lost",'Pipeline Data'!F$2:F$23,"<>Closed Won") -> 5 | D13: =SUMPRODUCT(('Pipeline Data'!D$2:D$23="APAC")*('Pipeline Data'!F$2:F$23<>"Closed Lost")*('Pipeline Data'!I$2:I$23)) -> 446750 | E13: =D13*$B$4 -> 446750 | F13: =$B$6*$B$7/3 -> 833333.33 | G13: =IF(F13=0,0,E13/F13) -> 0.5361 | H13: =E13-F13 -> -386583.33
A14: TOTAL | B14: =SUM(B11:B13) -> 2277000 | C14: =SUM(C11:C13) -> 16 | D14: =SUM(D11:D13) -> 1322150 | E14: =SUM(E11:E13) -> 1322150 | F14: =SUM(F11:F13) -> 2500000 | G14: =SUM(G11:G13) -> 1.58658 | H14: =SUM(H11:H13) -> -1177850
A16: QUOTA ATTAINMENT BY REP
A17: Sales Rep | B17: Region | C17: Closed Won ($) | D17: Pipeline (Weighted) ($) | E17: Scenario Total (1.00) | F17: Annual Quota ($) | G17: Attainment (%)
A18: James Okafor | B18: AMER | C18: =SUMPRODUCT(('Pipeline Data'!E$2:E$23="James Okafor")*('Pipeline Data'!F$2:F$23="Closed Won")*('Pipeline Data'!G$2:G$23)) -> 85000 | D18: =SUMPRODUCT(('Pipeline Data'!E$2:E$23="James Okafor")*('Pipeline Data'!F$2:F$23<>"Closed Won")*('Pipeline Data'!F$2:F$23<>"Closed Lost")*('Pipeline Data'!I$2:I$23)) -> 90000 | E18: =C18+D18*$B$4 -> 175000 | F18: =$B$6 -> 500000 | G18: =IF(F18=0,0,E18/F18) -> 0.35
A19: Sarah Nwachukwu | B19: AMER | C19: =SUMPRODUCT(('Pipeline Data'!E$2:E$23="Sarah Nwachukwu")*('Pipeline Data'!F$2:F$23="Closed Won")*('Pipeline Data'!G$2:G$23)) -> 0 | D19: =SUMPRODUCT(('Pipeline Data'!E$2:E$23="Sarah Nwachukwu")*('Pipeline Data'!F$2:F$23<>"Closed Won")*('Pipeline Data'!F$2:F$23<>"Closed Lost")*('Pipeline Data'!I$2:I$23)) -> 198750 | E19: =C19+D19*$B$4 -> 198750 | F19: =$B$6 -> 500000 | G19: =IF(F19=0,0,E19/F19) -> 0.3975
A20: Carlos Diaz | B20: AMER | C20: =SUMPRODUCT(('Pipeline Data'!E$2:E$23="Carlos Diaz")*('Pipeline Data'!F$2:F$23="Closed Won")*('Pipeline Data'!G$2:G$23)) -> 0 | D20: =SUMPRODUCT(('Pipeline Data'!E$2:E$23="Carlos Diaz")*('Pipeline Data'!F$2:F$23<>"Closed Won")*('Pipeline Data'!F$2:F$23<>"Closed Lost")*('Pipeline Data'!I$2:I$23)) -> 66150 | E20: =C20+D20*$B$4 -> 66150 | F20: =$B$6 -> 500000 | G20: =IF(F20=0,0,E20/F20) -> 0.1323
A21: Priya Sharma | B21: EMEA | C21: =SUMPRODUCT(('Pipeline Data'!E$2:E$23="Priya Sharma")*('Pipeline Data'!F$2:F$23="Closed Won")*('Pipeline Data'!G$2:G$23)) -> 110000 | D21: =SUMPRODUCT(('Pipeline Data'!E$2:E$23="Priya Sharma")*('Pipeline Data'!F$2:F$23<>"Closed Won")*('Pipeline Data'!F$2:F$23<>"Closed Lost")*('Pipeline Data'!I$2:I$23)) -> 147500 | E21: =C21+D21*$B$4 -> 257500 | F21: =$B$6 -> 500000 | G21: =IF(F21=0,0,E21/F21) -> 0.515
A22: Tobias Müller | B22: EMEA | C22: =SUMPRODUCT(('Pipeline Data'!E$2:E$23="Tobias Müller")*('Pipeline Data'!F$2:F$23="Closed Won")*('Pipeline Data'!G$2:G$23)) -> 62000 | D22: =SUMPRODUCT(('Pipeline Data'!E$2:E$23="Tobias Müller")*('Pipeline Data'!F$2:F$23<>"Closed Won")*('Pipeline Data'!F$2:F$23<>"Closed Lost")*('Pipeline Data'!I$2:I$23)) -> 116000 | E22: =C22+D22*$B$4 -> 178000 | F22: =$B$6 -> 500000 | G22: =IF(F22=0,0,E22/F22) -> 0.356
A23: Lin Wei | B23: APAC | C23: =SUMPRODUCT(('Pipeline Data'!E$2:E$23="Lin Wei")*('Pipeline Data'!F$2:F$23="Closed Won")*('Pipeline Data'!G$2:G$23)) -> 130000 | D23: =SUMPRODUCT(('Pipeline Data'!E$2:E$23="Lin Wei")*('Pipeline Data'!F$2:F$23<>"Closed Won")*('Pipeline Data'!F$2:F$23<>"Closed Lost")*('Pipeline Data'!I$2:I$23)) -> 194250 | E23: =C23+D23*$B$4 -> 324250 | F23: =$B$6 -> 500000 | G23: =IF(F23=0,0,E23/F23) -> 0.6485
A24: Raj Patel | B24: APAC | C24: =SUMPRODUCT(('Pipeline Data'!E$2:E$23="Raj Patel")*('Pipeline Data'!F$2:F$23="Closed Won")*('Pipeline Data'!G$2:G$23)) -> 0 | D24: =SUMPRODUCT(('Pipeline Data'!E$2:E$23="Raj Patel")*('Pipeline Data'!F$2:F$23<>"Closed Won")*('Pipeline Data'!F$2:F$23<>"Closed Lost")*('Pipeline Data'!I$2:I$23)) -> 122500 | E24: =C24+D24*$B$4 -> 122500 | F24: =$B$6 -> 500000 | G24: =IF(F24=0,0,E24/F24) -> 0.245
A25: TOTAL | C25: =SUM(C18:C24) -> 387000 | D25: =SUM(D18:D24) -> 935150 | E25: =SUM(E18:E24) -> 1322150 | F25: =SUM(F18:F24) -> 3500000 | G25: =IF(F25=0,0,E25/F25) -> 0.37775714

Sheet PBI Data Model
A1: Opp ID | B1: Opportunity Name | C1: Account Name | D1: Region | E1: Sales Rep | F1: Stage | G1: Amount ($) | H1: Probability (%) | I1: Weighted Amount ($) | J1: Close Date | K1: Lead Source | L1: Industry | M1: Best Case Forecast ($) | N1: Worst Case Forecast ($) | O1: Commit Forecast ($) | P1: Annual Quota ($) | Q1: Quarter
A2: OPP-001 | B2: CloudSync Enterprise License | C2: Meridian Health | D2: AMER | E2: James Okafor | F2: Proposal/Price Quote | G2: 120000 | H2: 0.75 | I2: =G2*H2 -> 90000 | J2: 45838 | K2: Outbound | L2: Healthcare | M2: =I2*1.15 -> 103500 | N2: =I2*0.8 -> 72000 | O2: =I2*1 -> 90000 | P2: 500000 | Q2: Q2 2025
A3: OPP-002 | B3: Analytics Pro Suite | C3: Apex Retail Group | D3: AMER | E3: James Okafor | F3: Closed Won | G3: 85000 | H3: 1 | I3: =G3*H3 -> 85000 | J3: 45792 | K3: Inbound | L3: Retail | M3: =I3*1.15 -> 97750 | N3: =I3*0.8 -> 68000 | O3: =I3*1 -> 85000 | P3: 500000 | Q3: Q2 2025
A4: OPP-003 | B4: DataBridge Platform | C4: Franklin Capital | D4: AMER | E4: Sarah Nwachukwu | F4: Needs Analysis | G4: 200000 | H4: 0.2 | I4: =G4*H4 -> 40000 | J4: 45869 | K4: Partner Referral | L4: Finance | M4: =I4*1.15 -> 46000 | N4: =I4*0.8 -> 32000 | O4: =I4*1 -> 40000 | P4: 500000 | Q4: Q3 2025
A5: OPP-004 | B5: NovaTech Core Bundle | C5: TechVentures Inc. | D5: AMER | E5: Sarah Nwachukwu | F5: Value Proposition | G5: 55000 | H5: 0.5 | I5: =G5*H5 -> 27500 | J5: 45823 | K5: Web | L5: Technology | M5: =I5*1.15 -> 31625 | N5: =I5*0.8 -> 22000 | O5: =I5*1 -> 27500 | P5: 500000 | Q5: Q2 2025
A6: OPP-005 | B6: Premium Support Pack | C6: GlobalEdge LLC | D6: AMER | E6: James Okafor | F6: Closed Lost | G6: 30000 | H6: 0 | I6: =G6*H6 -> 0 | J6: 45777 | K6: Outbound | L6: Consulting | M6: =I6*1.15 -> 0 | N6: =I6*0.8 -> 0 | O6: =I6*1 -> 0 | P6: 500000 | Q6: Q2 2025
A7: OPP-006 | B7: AI Insights Module | C7: StreamlineOps | D7: AMER | E7: Carlos Diaz | F7: Perception Analysis | G7: 95000 | H7: 0.65 | I7: =G7*H7 -> 61750 | J7: 45853 | K7: Event | L7: Manufacturing | M7: =I7*1.15 -> 71012.5 | N7: =I7*0.8 -> 49400 | O7: =I7*1 -> 61750 | P7: 500000 | Q7: Q3 2025
A8: OPP-007 | B8: SMB Starter Plan | C8: Bright Ideas Co. | D8: AMER | E8: Carlos Diaz | F8: Needs Analysis | G8: 22000 | H8: 0.2 | I8: =G8*H8 -> 4400 | J8: 45900 | K8: Inbound | L8: Education | M8: =I8*1.15 -> 5060 | N8: =I8*0.8 -> 3520 | O8: =I8*1 -> 4400 | P8: 500000 | Q8: Q3 2025
A9: OPP-008 | B9: Enterprise Suite Renewal | C9: Hartwell Corp | D9: AMER | E9: Sarah Nwachukwu | F9: Proposal/Price Quote | G9: 175000 | H9: 0.75 | I9: =G9*H9 -> 131250 | J9: 45838 | K9: Outbound | L9: Financial Services | M9: =I9*1.15 -> 150937.5 | N9: =I9*0.8 -> 105000 | O9: =I9*1 -> 131250 | P9: 500000 | Q9: Q2 2025
A10: OPP-009 | B10: CloudSync EMEA Bundle | C10: Nordic Systems AB | D10: EMEA | E10: Priya Sharma | F10: Closed Won | G10: 110000 | H10: 1 | I10: =G10*H10 -> 110000 | J10: 45797 | K10: Partner Referral | L10: Technology | M10: =I10*1.15 -> 126500 | N10: =I10*0.8 -> 88000 | O10: =I10*1 -> 110000 | P10: 500000 | Q10: Q2 2025
A11: OPP-010 | B11: DataBridge EU | C11: Vega Pharmaceuticals | D11: EMEA | E11: Priya Sharma | F11: Value Proposition | G11: 145000 | H11: 0.5 | I11: =G11*H11 -> 72500 | J11: 45869 | K11: Inbound | L11: Pharma | M11: =I11*1.15 -> 83375 | N11: =I11*0.8 -> 58000 | O11: =I11*1 -> 72500 | P11: 500000 | Q11: Q3 2025
A12: OPP-011 | B12: Analytics Platform | C12: Atlas Logistics | D12: EMEA | E12: Tobias Müller | F12: Proposal/Price Quote | G12: 88000 | H12: 0.75 | I12: =G12*H12 -> 66000 | J12: 45823 | K12: Outbound | L12: Logistics | M12: =I12*1.15 -> 75900 | N12: =I12*0.8 -> 52800 | O12: =I12*1 -> 66000 | P12: 500000 | Q12: Q2 2025
A13: OPP-012 | B13: Core License Expansion | C13: Luminos Bank | D13: EMEA | E13: Tobias Müller | F13: Needs Analysis | G13: 250000 | H13: 0.2 | I13: =G13*H13 -> 50000 | J13: 45930 | K13: Inbound | L13: Banking | M13: =I13*1.15 -> 57500 | N13: =I13*0.8 -> 40000 | O13: =I13*1 -> 50000 | P13: 500000 | Q13: Q3 2025
... A23: OPP-022 | B23: SMB Package SEA | C23: ByteLogic MY | D23: APAC | E23: Lin Wei | F23: Closed Lost | G23: 18000 | H23: 0 | I23: =G23*H23 -> 0 | J23: 45778 | K23: Web | L23: Technology | M23: =I23*1.15 -> 0 | N23: =I23*0.8 -> 0 | O23: =I23*1 -> 0 | P23: 500000 | Q23: Q2 2025
A24: TOTALS | G24: =SUM(G2:G23) -> 2325000 | I24: =SUM(I2:I23) -> 1322150 | M24: =SUM(M2:M23) -> 1520472.5 | N24: =SUM(N2:N23) -> 1057720 | O24: =SUM(O2:O23) -> 1322150 | P24: =SUM(P2:P23) -> 11000000
